pyalmond/__init__.py
pyalmond-0.0.3.dist-info/LICENSE
pyalmond-0.0.3.dist-info/METADATA
pyalmond-0.0.3.dist-info/WHEEL
pyalmond-0.0.3.dist-info/top_level.txt
pyalmond-0.0.3.dist-info/RECORD
