Metadata-Version: 2.1
Name: pyalmond
Version: 0.0.3
Summary: Python module to talk to the Web Almond API.
Home-page: https://github.com/stanford-oval/pyalmond
Author: Giovanni Campagna
Author-email: gcampagn@cs.stanford.edu
License: BSD-3-Clause
Platform: any
Requires-Dist: aiohttp
